socketer/__init__.py
socketer/abstract.py
socketer/client.py
socketer/server.py
weesocket/__init__.py
weesocket/abstract.py
weesocket/client.py
weesocket/server.py
weesocket-1.0.1.dist-info/LICENSE
weesocket-1.0.1.dist-info/METADATA
weesocket-1.0.1.dist-info/WHEEL
weesocket-1.0.1.dist-info/top_level.txt
weesocket-1.0.1.dist-info/RECORD
