Metadata-Version: 2.1
Name: weesocket
Version: 1.0.1
Summary: Tiny socket wrapper
Home-page: https://gitlab.com/katry/weesocket
Author: Patrik Katrenak
Author-email: patrik@katryapps.com
License: UNKNOWN
Platform: any
Classifier: Programming Language :: Python :: 3
Classifier: License :: OSI Approved :: GNU Lesser General Public License v3 (LGPLv3)
Classifier: Operating System :: OS Independent
Requires-Python: >=3.9
License-File: LICENSE
Requires-Dist: rsa
Provides-Extra: dev
Requires-Dist: orjson ; extra == 'dev'
Requires-Dist: pytest ; extra == 'dev'
Requires-Dist: wheel ; extra == 'dev'
Requires-Dist: twine ; extra == 'dev'
Provides-Extra: orjson
Requires-Dist: orjson ; extra == 'orjson'
Provides-Extra: ujson
Requires-Dist: ujson ; extra == 'ujson'
